PyAase/__init__.py
PyAase/ead.py
pyaase-0.0.3.dist-info/METADATA
pyaase-0.0.3.dist-info/WHEEL
pyaase-0.0.3.dist-info/licenses/LICENSE
pyaase-0.0.3.dist-info/RECORD
