Metadata-Version: 2.1
Name: PyAase
Version: 0.0.3
Summary: Python package for personal development
Project-URL: Homepage, https://github.com/AngeloBurt/packaging-py-develop-venus
Project-URL: Bug Tracker, https://github.com/AngeloBurt/packaging-py-develop-venus/issues
Author-email: AngeloBurt <542685010@qq.com>
License-File: LICENSE
Classifier: License :: OSI Approved :: MIT License
Classifier: Operating System :: OS Independent
Classifier: Programming Language :: Python :: 3
Requires-Python: >=3.7
